collective.recipe.vscode-0.1.9-py3.8-nspkg.pth
collective/recipe/vscode/__init__.py
collective/recipe/vscode/recipes.py
collective/recipe/vscode/recipes.rst
collective/recipe/vscode/settings_mappings.json
collective/recipe/vscode/tests/__init__.py
collective/recipe/vscode/tests/test_docs.py
collective/recipe/vscode/tests/test_recipes.py
collective/recipe/vscode/tests/Products/VSCodeTestProduct/__init__.py
collective/recipe/vscode/tests/Products/VSCodeTestProduct/production.txt
collective/recipe/vscode/tests/develop/vscodetest_pkg1/.gitignore
collective/recipe/vscode/tests/develop/vscodetest_pkg1/LICENSE
collective/recipe/vscode/tests/develop/vscodetest_pkg1/MANIFEST.in
collective/recipe/vscode/tests/develop/vscodetest_pkg1/README.rst
collective/recipe/vscode/tests/develop/vscodetest_pkg1/setup.py
collective/recipe/vscode/tests/develop/vscodetest_pkg1/vscodetest_pkg1/__init__.py
collective/recipe/vscode/tests/develop/vscodetest_pkg1/vscodetest_pkg1/sublimtexttest_pkg1.py
collective.recipe.vscode-0.1.9.dist-info/METADATA
collective.recipe.vscode-0.1.9.dist-info/WHEEL
collective.recipe.vscode-0.1.9.dist-info/entry_points.txt
collective.recipe.vscode-0.1.9.dist-info/namespace_packages.txt
collective.recipe.vscode-0.1.9.dist-info/top_level.txt
collective.recipe.vscode-0.1.9.dist-info/RECORD
