Metadata-Version: 2.1
Name: collective.recipe.vscode
Version: 0.1.9
Summary: Visual Studio Code configuration for buildout-based Python projects
Home-page: https://github.com/nazrulworld/collective.recipe.vscode
Author: Md Nazrul Islam
Author-email: email2nazrul@gmail.com
License: GPL version 2
Keywords: python buildout plone vscode jedi sublimelinter buildout-recipe anaconda
Platform: UNKNOWN
Classifier: Environment :: Web Environment
Classifier: Development Status :: 4 - Beta
Classifier: Framework :: Plone
Classifier: Framework :: Plone :: 4.3
Classifier: Framework :: Plone :: 5.0
Classifier: Framework :: Plone :: 5.1
Classifier: Framework :: Plone :: 5.2
Classifier: Programming Language :: Python
Classifier: Programming Language :: Python :: 2.7
Classifier: Programming Language :: Python :: 3.4
Classifier: Programming Language :: Python :: 3.5
Classifier: Programming Language :: Python :: 3.6
Classifier: Programming Language :: Python :: 3.7
Classifier: Programming Language :: Python :: 3.8
Classifier: Programming Language :: Python :: 3.9
Classifier: Programming Language :: Python :: 3.10
Classifier: Operating System :: OS Independent
Classifier: Topic :: Software Development :: Build Tools
Classifier: License :: OSI Approved :: GNU General Public License v2 (GPLv2)
Requires-Dist: setuptools
Requires-Dist: zc.buildout
Requires-Dist: zc.recipe.egg
Provides-Extra: test
Requires-Dist: zope.testing ; extra == 'test'
Requires-Dist: zc.buildout[test] ; extra == 'test'
Requires-Dist: zc.recipe.egg ; extra == 'test'
